kakaopy/__init__.py
kakaopy/kakaopy.py
kakaopy-0.2.0.dist-info/LICENSE
kakaopy-0.2.0.dist-info/METADATA
kakaopy-0.2.0.dist-info/WHEEL
kakaopy-0.2.0.dist-info/top_level.txt
kakaopy-0.2.0.dist-info/RECORD
