Metadata-Version: 2.1
Name: kakaopy
Version: 0.2.0
Summary: kakao search API customizing
Home-page: https://github.com/SeoJeongYeop/kakaopy
Author: Jeongyeop Seo
Author-email: sjyswe99@gmail.com
License: MIT
Platform: UNKNOWN
Classifier: License :: OSI Approved :: MIT License
Classifier: Programming Language :: Python :: 3
Classifier: Programming Language :: Python :: 3.8
Classifier: Programming Language :: Python :: 3.9
License-File: LICENSE
